MANIFEST.in
README.rst
setup.cfg
setup.py
rpncdf/__init__.py
rpncdf/o.dict
rpncdf/rpncdf.py
rpncdf.egg-info/PKG-INFO
rpncdf.egg-info/SOURCES.txt
rpncdf.egg-info/dependency_links.txt
rpncdf.egg-info/entry_points.txt
rpncdf.egg-info/requires.txt
rpncdf.egg-info/top_level.txt
rpncdf.egg-info/zip-safe