Metadata-Version: 1.1
Name: rpncdf
Version: 0.1
Summary: Converts RPN standard files to NetCDF
Home-page: http://github.com/doylejg/rpncdf
Author: Jonathan G. Doyle
Author-email: jonathan.g.doyle@gmail.com
License: LGPLv3+
Keywords: netcdf rpn gem wrf environmentcanada eccc ec
Platform: UNKNOWN
Classifier: Development Status :: 4 - Beta
Classifier: License :: OSI Approved :: GNU Lesser General Public License v3 or later (LGPLv3+)
Classifier: Programming Language :: Python :: 2.7
Classifier: Intended Audience :: Science/Research
Classifier: Topic :: Scientific/Engineering :: Atmospheric Science
